{
	"name": "Mulitlanguage",
	"properties": {
		"folder": {
			"name": "dpi30testeusdj"
		},
		"nbformat": 4,
		"nbformat_minor": 2,
		"bigDataPool": {
			"referenceName": "testspark",
			"type": "BigDataPoolReference"
		},
		"sessionProperties": {
			"driverMemory": "56g",
			"driverCores": 8,
			"executorMemory": "56g",
			"executorCores": 8,
			"numExecutors": 1,
			"runAsWorkspaceSystemIdentity": false,
			"conf": {
				"spark.dynamicAllocation.enabled": "true",
				"spark.dynamicAllocation.minExecutors": "1",
				"spark.dynamicAllocation.maxExecutors": "4",
				"spark.autotune.trackingId": "8fcb8c87-b92d-4164-86a8-ca1107621177"
			}
		},
		"metadata": {
			"saveOutput": true,
			"synapse_widget": {
				"version": "0.1"
			},
			"enableDebugMode": false,
			"kernelspec": {
				"name": "synapse_pyspark",
				"display_name": "Synapse PySpark"
			},
			"language_info": {
				"name": "python"
			},
			"a365ComputeOptions": {
				"id": "/subscriptions/a802af10-3082-4ea6-b3db-542043a41e96/resourceGroups/rg-dpi30-test-eus-001/providers/Microsoft.Synapse/workspaces/dpi30-test-eus-syn-01/bigDataPools/testspark",
				"name": "testspark",
				"type": "Spark",
				"endpoint": "https://dpi30-test-eus-syn-01.dev.azuresynapse.net/livyApi/versions/2019-11-01-preview/sparkPools/testspark",
				"auth": {
					"type": "AAD",
					"authResource": "https://dev.azuresynapse.net",
					"authHeader": null
				},
				"sparkVersion": "3.1",
				"nodeCount": 3,
				"cores": 8,
				"memory": 56,
				"extraHeader": null
			},
			"sessionKeepAliveTimeout": 30
		},
		"cells": [
			{
				"cell_type": "code",
				"metadata": {
					"microsoft": {
						"language": "scala"
					}
				},
				"source": [
					"%%spark\n",
					"val scala:String= \"scala\""
				],
				"execution_count": 5
			},
			{
				"cell_type": "code",
				"metadata": {
					"jupyter": {
						"source_hidden": false,
						"outputs_hidden": false
					},
					"nteract": {
						"transient": {
							"deleting": false
						}
					},
					"microsoft": {
						"language": "python"
					}
				},
				"source": [
					"%%pyspark\n",
					"python:str =\"python\""
				],
				"execution_count": 6
			},
			{
				"cell_type": "code",
				"metadata": {
					"jupyter": {
						"source_hidden": false,
						"outputs_hidden": false
					},
					"nteract": {
						"transient": {
							"deleting": false
						}
					},
					"microsoft": {
						"language": "scala"
					}
				},
				"source": [
					"%%spark\n",
					"println(python)"
				],
				"execution_count": 7
			},
			{
				"cell_type": "markdown",
				"metadata": {
					"nteract": {
						"transient": {
							"deleting": false
						}
					}
				},
				"source": [
					"As per the above error , we know that the variables and data is not transferable across different languages "
				]
			},
			{
				"cell_type": "code",
				"metadata": {
					"jupyter": {
						"source_hidden": false,
						"outputs_hidden": false
					},
					"nteract": {
						"transient": {
							"deleting": false
						}
					},
					"microsoft": {
						"language": "python"
					}
				},
				"source": [
					"%%pyspark\n",
					"print(scala)"
				]
			}
		]
	}
}